afbf/__init__.py
afbf/utilities.py
afbf/Classes/Field.py
afbf/Classes/PeriodicFunction.py
afbf/Classes/RandomProcess.py
afbf/Classes/SpatialData.py
afbf/Classes/__init__.py
afbf/Simulation/TurningBands.py
afbf/Simulation/__init__.py
examples/__init__.py
pyafbf-0.2.9.dist-info/licenses/AUTHORS.rst
pyafbf-0.2.9.dist-info/licenses/LICENSE.rst
pyafbf-0.2.9.dist-info/METADATA
pyafbf-0.2.9.dist-info/WHEEL
pyafbf-0.2.9.dist-info/entry_points.txt
pyafbf-0.2.9.dist-info/top_level.txt
pyafbf-0.2.9.dist-info/RECORD
