Metadata-Version: 2.4
Name: PyAFBF
Version: 0.2.9
Summary: Generate image textures from anisotropic fractional Brownian fields
Home-page: https://github.com/fjprichard/PyAFBF/
Author: Frederic Richard
Author-email: frederic.richard@univ-amu.fr
License: GPLv3
Project-URL: Documentation, https://fjprichard.github.io/PyAFBF/
Project-URL: Source, https://github.com/fjprichard/PyAFBF/
Project-URL: Tracker, https://github.com/fjprichard/PyAFBF/issues
Keywords: anisotropic fractional Brownian field,simulation,image texture
Platform: Linux
Platform: MacOSX
Platform: Windows
Classifier: License :: OSI Approved :: GNU General Public License v3 (GPLv3)
Classifier: Development Status :: 5 - Production/Stable
Classifier: Intended Audience :: Science/Research
Classifier: Intended Audience :: End Users/Desktop
Classifier: Intended Audience :: Developers
Classifier: Natural Language :: English
Classifier: Operating System :: OS Independent
Classifier: Programming Language :: Python :: 3.11
Classifier: Topic :: Scientific/Engineering :: Image Processing
License-File: LICENSE.rst
License-File: AUTHORS.rst
Requires-Dist: numpy>=1.26.4
Requires-Dist: matplotlib>=3.10.0
Requires-Dist: scipy>=1.16.1
Requires-Dist: imageio>=2.37.0
Requires-Dist: pickle
Provides-Extra: dev
Requires-Dist: doctest; extra == "dev"
Dynamic: author
Dynamic: author-email
Dynamic: classifier
Dynamic: description
Dynamic: home-page
Dynamic: keywords
Dynamic: license
Dynamic: license-file
Dynamic: platform
Dynamic: project-url
Dynamic: provides-extra
Dynamic: requires-dist
Dynamic: summary
